usms/__init__.py
usms/__main__.py
usms/cli.py
usms/factory.py
usms/config/__init__.py
usms/config/constants.py
usms/core/__init__.py
usms/core/auth.py
usms/core/client.py
usms/core/protocols.py
usms/core/state_manager.py
usms/exceptions/__init__.py
usms/exceptions/errors.py
usms/models/__init__.py
usms/models/account.py
usms/models/meter.py
usms/models/tariff.py
usms/parsers/__init__.py
usms/parsers/account_info_parser.py
usms/parsers/asp_state_parser.py
usms/parsers/error_message_parser.py
usms/parsers/meter_consumptions_parser.py
usms/parsers/meter_info_parser.py
usms/services/__init__.py
usms/services/account.py
usms/services/meter.py
usms/services/async_/__init__.py
usms/services/async_/account.py
usms/services/async_/meter.py
usms/services/sync/__init__.py
usms/services/sync/account.py
usms/services/sync/meter.py
usms/storage/__init__.py
usms/storage/base_storage.py
usms/storage/csv_storage.py
usms/storage/sqlite_storage.py
usms/utils/__init__.py
usms/utils/decorators.py
usms/utils/helpers.py
usms/utils/logging_config.py
usms-0.9.2.dist-info/METADATA
usms-0.9.2.dist-info/WHEEL
usms-0.9.2.dist-info/licenses/LICENSE
usms-0.9.2.dist-info/RECORD
