Metadata-Version: 2.4
Name: usms
Version: 0.9.2
Summary: An unofficial Python library to interface with your USMS account and smart meters.
Project-URL: homepage, https://github.com/azsaurr/usms
Project-URL: source, https://github.com/azsaurr/usms
Project-URL: changelog, https://github.com/azsaurr/usms/blob/main/CHANGELOG.md
Project-URL: releasenotes, https://github.com/azsaurr/usms/releases
Project-URL: documentation, https://github.com/azsaurr/usms
Project-URL: issues, https://github.com/azsaurr/usms/issues
Author-email: AZ <102905929+azsaurr@users.noreply.github.com>
License: MIT License
License-File: LICENSE
Requires-Python: <4.0,>=3.10
Requires-Dist: httpx[http2]>=0.28.1
Requires-Dist: pandas>=2.2.3
